<?xml version="1.0" encoding="UTF-8"?>
<root> <import src="public_network.xml" />
	<!-- 
	devicetype:			设备类型名称
	ismulticoltype:		是否允许采集方式多选
	majortype:			主要分类（可以理解为设备类型）
	minortype:			次要分类
	manufacturer:		厂商
	devicetype_zh:		设备类型中文描述
	 -->
	<devicetypeinfo devicetype="Freecomm_Switch" ismulticoltype="true" majortype="network" minortype="Switch" manufacturer="Freecomm" devicetype_zh="斐讯交换机">
		
		<!-- 用于定位设备为该类设备的多个sysoid标识，如果snmp采集为sysoid，如果其他方式自行定义 -->
		<devicetypes>
				<devicetype sysoid="1.3.6.1.4.1.33619.1.124"/>
				<devicetype sysoid="1.3.6.1.4.1.33619.1.147.0"/>

		</devicetypes>
		
		<!-- 该设备类型定义的命令，用于合并命令执行 -->
		<commands>
			<!-- coltype:采集方式，comid：命令ID，command：命令 -->
			
			<command coltype="SNMP" comid="numberOfCPU" command=""/>   <!--CPU个数-->
			<command coltype="SNMP" comid="totalMemSize" command="1.3.6.1.4.1.33619.9.48.2"/>   <!--内存总容量-->
			<command coltype="SNMP" comid="cpuUsage"     command="1.3.6.1.4.1.33619.9.109.1.1.1.1.5"/>  <!--CPU平均利用率-->
			<command coltype="SNMP" comid="memUsage"  command="1.3.6.1.4.1.33619.9.48.1"/>   <!--内存利用率-->
			<command coltype="SNMP" comid="memPoolFree"  command=""/>   <!--内存池可用容量-->		


			
		</commands>
		
		<!-- 描述该类设备的所有指标采集,一行对应一个指标 -->
		<resources>
			
			<!-- CPU个数 -->
			<!--<resource kpiid="N1cpuNum" coltype="SNMP" value="" valuetype="Integer" unit="">
				<collects>
					<collect exeorder="10" comid="numberOfCPU" select="" merge="count" deal=""/>				
				</collects>
				
				<kpipolicy table="res_d_N1cpuNum" field="value" fieldtype="" willalert=""
					alertexp1="" alertdesc1="" alertexp2="" alertdesc2="" alertexp3=""
					alertdesc3="" alertexp4="" alertdesc4="" alertexp5="" alertdesc5=""
					alertcontin="1" alertype="" circle="1440" storefactor="1"/>
					
			</resource> -->
			
			<!-- 内存总容量 -->
			<resource kpiid="N1totalMemSize" coltype="SNMP" value="" valuetype="Float" unit="Byte">
				<collects>
					<collect exeorder="10" comid="totalMemSize" select="" merge="sum" deal=""/>				
				</collects>
				
				<kpipolicy table="res_d_N1totalMemSize" field="value" fieldtype="" willalert=""
					alertexp1="" alertdesc1="" alertexp2="" alertdesc2="" alertexp3=""
					alertdesc3="" alertexp4="" alertdesc4="" alertexp5="" alertdesc5=""
					alertcontin="1" alertype="" circle="1440" storefactor="1"/>
					
			</resource>
			
			
			<!-- CPU平均利用率 -->
			<resource kpiid="N1cpuUsage" coltype="SNMP" value="" valuetype="Float" unit="%">		
				<collects>				
					<collect exeorder="10" comid="cpuUsage" select="" merge="max" deal=""/>
				</collects>
			
				
				<kpipolicy table="res_d_N1cpuUsage" field="value" fieldtype="" willalert="y"
					alertexp1="${value}&lt;85" alertdesc1="CPU平均利用率恢复正常，当前值为${value}%。" alertexp2="" alertdesc2="" alertexp3="${value}>=85"
					alertdesc3="CPU平均利用率大于等于${trigervalue1}%，当前值为${value}%。" alertexp4="${value}>=95" alertdesc4="CPU平均利用率大于等于${trigervalue1}%，当前值为${value}%。" alertexp5="" alertdesc5=""
					alertcontin="1"   circle="5" storefactor="1"/>
				
			</resource>
			
			<!-- 内存利用率 -->
			<resource kpiid="N1memUsage" coltype="SNMP" value="" valuetype="Float" unit="%">
				<collects>
					<collect exeorder="10" comid="memUsage" select="" merge="max" deal=""/>	
				</collects>
				
				<kpipolicy table="res_d_N1memUsage" field="value" fieldtype="" willalert="y"
					alertexp1="${value}&lt;85" alertdesc1="内存利用率恢复正常，当前值为${value}%。" alertexp2="" alertdesc2="" alertexp3="${value}>=85"
					alertdesc3="内存利用率大于等于${trigervalue1}%，当前值为${value}%。" alertexp4="${value}>=95" alertdesc4="内存利用率大于等于${trigervalue1}%，当前值为${value}%。" alertexp5="" alertdesc5=""
					alertcontin="1"   circle="5" storefactor="1"/>
				
			</resource>
			
			<!-- 内存池可用容量 -->
			<!--<resource kpiid="N1memPoolFree" coltype="SNMP" value="" valuetype="Float" unit="Byte">
				<collects>
					<collect exeorder="10" comid="memPoolFree" select="" merge="sum" deal=""/>
				</collects>
				
				<kpipolicy table="res_d_N1memPoolFree" field="value" fieldtype="" willalert=""
					alertexp1="" alertdesc1="" alertexp2="" alertdesc2="" alertexp3=""
					alertdesc3="" alertexp4="" alertdesc4="" alertexp5="" alertdesc5=""
					alertcontin="1" alertype="" circle="15" storefactor="1"/>
				
			</resource> -->
			
			
			
		
			
		</resources>
	</devicetypeinfo>
</root>